README.rst
setup.py
tests/__init__.py
tests/test_encoder.py
tests/test_treelstm.py
tests/test_treenet.py
treenet/__init__.py
treenet/encoder.py
treenet/treelstm.py
treenet/treenet.py
treenet.egg-info/PKG-INFO
treenet.egg-info/SOURCES.txt
treenet.egg-info/dependency_links.txt
treenet.egg-info/requires.txt
treenet.egg-info/top_level.txt