Metadata-Version: 1.1
Name: treenet
Version: 0.0.1
Summary: Recursive Neural Networks for PyTorch
Home-page: https://github.com/epfl-lara/treenet
Author: Romain Edelmann
Author-email: romain.edelmann@epfl.ch
License: GPLv3
Download-URL: https://github.com/epfl-lara/treenet/archive/0.0.1.tar.gz
Keywords: recursive neural network tree lstm tree-lstm
Platform: UNKNOWN
Classifier: Development Status :: 3 - Alpha
Classifier: License :: OSI Approved :: GNU General Public License v3 (GPLv3)
